{
  "name": "Tradition der Kristallomanten IV",
  "type": "vorteil",
  "system": {
    "voraussetzung": "Attribut KL 10, Vorteil Tradition der Kristallomanten III",
    "gruppe": 5,
    "text": "Bedingung: 2 weitere Attribute auf insgesamt 16.\n\n8 Punkte können zur Verbesserung der Tradition verwendet werden. "
  },
  "_id": "10PeTR8W4A0QILOH",
  "effects": [],
  "_stats": {
    "coreVersion": "12.331",
    "systemId": null,
    "systemVersion": null,
    "createdTime": null,
    "modifiedTime": null,
    "lastModifiedBy": null,
    "compendiumSource": null,
    "duplicateSource": null
  },
  "img": "icons/svg/item-bag.svg",
  "folder": null,
  "sort": 0,
  "ownership": {
    "default": 0
  },
  "flags": {},
  "_key": "!items!10PeTR8W4A0QILOH"
}
