{
  "name": "Tiergeist (Löwe)",
  "type": "vorteil",
  "system": {
    "voraussetzung": "Vorteil Tradition der Anach-Nurim I ODER Vorteil Tradition der Durro-dun I ODER Vorteil Tradition der Schamanen I, Kein Vorteil Tiergeist (Affe) ODER Vorteil Tradition der Schamanen I, Kein Vorteil Tiergeist (Bär) ODER Vorteil Tradition der Schamanen I, Kein Vorteil Tiergeist (Elefant) ODER Vorteil Tradition der Schamanen I, Kein Vorteil Tiergeist (Eule) ODER Vorteil Tradition der Schamanen I, Kein Vorteil Tiergeist (Falke) ODER Vorteil Tradition der Schamanen I, Kein Vorteil Tiergeist (Fischotter) ODER Vorteil Tradition der Schamanen I, Kein Vorteil Tiergeist (Fuchs/Mungo) ODER Vorteil Tradition der Schamanen I, Kein Vorteil Tiergeist (Gebirgsbock) ODER Vorteil Tradition der Schamanen I, Kein Vorteil Tiergeist (Mammut) ODER Vorteil Tradition der Schamanen I, Kein Vorteil Tiergeist (Rabe) ODER Vorteil Tradition der Schamanen I, Kein Vorteil Tiergeist (Schlange) ODER Vorteil Tradition der Schamanen I, Kein Vorteil Tiergeist (Stier) ODER Vorteil Tradition der Schamanen I, Kein Vorteil Tiergeist (Wildkatze/Panther) ODER Vorteil Tradition der Schamanen I, Kein Vorteil Tiergeist (Wildschwein) ODER Vorteil Tradition der Schamanen I, Kein Vorteil Tiergeist (Wolf/Khoramsbestie) ODER Vorteil Tradition der Schamanen I",
    "gruppe": 8,
    "text": "Archetyp: Anführer\nWertebonus: Autorität, Willenskraft, MU\nVerwandlung: Maul (2W6+2 TP waffenlos, Einschüchtern +4), Mähne (Anführen +4, Furcht-Effekte sinken um 1 Stufe)\nZauber: Ängste lindern, Armatrutz, Katzenaugen, Kusch!, Standfest\n\n"
  },
  "_id": "W8BObex9ujivZKHT",
  "effects": [],
  "_stats": {
    "coreVersion": "12.331",
    "systemId": null,
    "systemVersion": null,
    "createdTime": null,
    "modifiedTime": null,
    "lastModifiedBy": null,
    "compendiumSource": null,
    "duplicateSource": null
  },
  "img": "icons/svg/item-bag.svg",
  "folder": null,
  "sort": 0,
  "ownership": {
    "default": 0
  },
  "flags": {},
  "_key": "!items!W8BObex9ujivZKHT"
}
