{
  "name": "Unverwüstlich",
  "type": "vorteil",
  "system": {
    "voraussetzung": "Attribut KO 10",
    "gruppe": 1,
    "text": "Deine WS steigt um 1 Punkt.\n\nWenn Zähigkeitsproben zum Ignorieren von Kampfunfähigkeit misslingen, erleidest du keine Erschöpfung."
  },
  "_id": "tzmw4qtymc9SZB7V",
  "effects": [],
  "_stats": {
    "coreVersion": "12.331",
    "systemId": null,
    "systemVersion": null,
    "createdTime": null,
    "modifiedTime": null,
    "lastModifiedBy": null,
    "compendiumSource": null,
    "duplicateSource": null
  },
  "img": "icons/svg/item-bag.svg",
  "folder": null,
  "sort": 0,
  "ownership": {
    "default": 0
  },
  "flags": {},
  "_key": "!items!tzmw4qtymc9SZB7V"
}
