{
  "name": "Madas Spiegel",
  "type": "zauber",
  "img": "systems/Ilaris/assets/images/skills/magic-talent.svg",
  "system": {
    "fertigkeiten": "Hellsicht, Verständigung",
    "fertigkeit_ausgewaehlt": "auto",
    "text": "Die Spiegelung des Mondes auf der Wasseroberfläche verwandelt sich in das Abbild des Ziels. Zusätzlich kannst du kleine Teile des Hintergrunds erkennen und spürst flüchtig die Gefühlseindrücke deines Zieles. Dieses erinnert sich währenddessen an dich.",
    "maechtig": "",
    "schwierigkeit": "12",
    "modifikationen": "",
    "vorbereitung": "4 Minuten",
    "ziel": "Einzelperson",
    "reichweite": "dereweit",
    "wirkungsdauer": "16 Initiativphasen",
    "kosten": "8 AsP",
    "erlernen": "Hex 18; Dru, Srl 20",
    "pw": 0,
    "gruppe": 0
  },
  "effects": [],
  "folder": null,
  "sort": 0,
  "flags": {},
  "_id": "TCZujaQMQkWkS8Gb",
  "_stats": {
    "coreVersion": "12.331",
    "systemId": null,
    "systemVersion": null,
    "createdTime": null,
    "modifiedTime": null,
    "lastModifiedBy": null,
    "compendiumSource": null,
    "duplicateSource": null
  },
  "ownership": {
    "default": 0,
    "b5zxAh2tnhbWdvfZ": 3
  },
  "_key": "!items!TCZujaQMQkWkS8Gb"
}
