{
  "name": "Zunge lähmen",
  "type": "zauber",
  "img": "systems/Ilaris/assets/images/skills/magic-talent.svg",
  "system": {
    "fertigkeiten": "Eigenschaften",
    "fertigkeit_ausgewaehlt": "auto",
    "text": "Dein Opfer kann seine Zunge nicht mehr bewegen und kann keine verständlichen Äußerungen von sich geben. Wenn ein Zauber oder eine Liturgie eine gesprochene Formel oder Gebet benötigt, muss das Ziel die Zaubertechnik ignorieren.",
    "maechtig": "",
    "schwierigkeit": "Magieresistenz",
    "modifikationen": "",
    "vorbereitung": "2 Aktionen",
    "ziel": "Einzelperson",
    "reichweite": "8 Schritt",
    "wirkungsdauer": "1 Stunde",
    "kosten": "8 AsP",
    "erlernen": "Dru 14; Geo 16; Alch, Hex, Sch 18",
    "pw": 0,
    "gruppe": 0
  },
  "effects": [],
  "folder": null,
  "sort": 0,
  "flags": {},
  "_id": "8Ji21p9e1W9ClNsW",
  "_stats": {
    "coreVersion": "12.331",
    "systemId": null,
    "systemVersion": null,
    "createdTime": null,
    "modifiedTime": null,
    "lastModifiedBy": null,
    "compendiumSource": null,
    "duplicateSource": null
  },
  "ownership": {
    "default": 0,
    "b5zxAh2tnhbWdvfZ": 3
  },
  "_key": "!items!8Ji21p9e1W9ClNsW"
}
